odoo/addons/storage_backend_ftp/README.rst
odoo/addons/storage_backend_ftp/__init__.py
odoo/addons/storage_backend_ftp/__manifest__.py
odoo/addons/storage_backend_ftp/components/__init__.py
odoo/addons/storage_backend_ftp/components/ftp_adapter.py
odoo/addons/storage_backend_ftp/i18n/storage_backend_ftp.pot
odoo/addons/storage_backend_ftp/models/__init__.py
odoo/addons/storage_backend_ftp/models/storage_backend.py
odoo/addons/storage_backend_ftp/readme/CONTRIBUTORS.rst
odoo/addons/storage_backend_ftp/readme/DESCRIPTION.rst
odoo/addons/storage_backend_ftp/static/description/icon.png
odoo/addons/storage_backend_ftp/static/description/index.html
odoo/addons/storage_backend_ftp/tests/__init__.py
odoo/addons/storage_backend_ftp/tests/test_ftp.py
odoo/addons/storage_backend_ftp/views/backend_storage_view.xml
odoo13_addon_storage_backend_ftp-13.0.1.2.0.dist-info/METADATA
odoo13_addon_storage_backend_ftp-13.0.1.2.0.dist-info/WHEEL
odoo13_addon_storage_backend_ftp-13.0.1.2.0.dist-info/top_level.txt
odoo13_addon_storage_backend_ftp-13.0.1.2.0.dist-info/RECORD
